LICENSE
MANIFEST.in
README.md
setup.py
pudl/__init__.py
pudl/ad_computer.py
pudl/ad_group.py
pudl/ad_object.py
pudl/ad_query.py
pudl/ad_user.py
pudl/helper.py
pudl/version.py
pudl.egg-info/PKG-INFO
pudl.egg-info/SOURCES.txt
pudl.egg-info/dependency_links.txt
pudl.egg-info/entry_points.txt
pudl.egg-info/pbr.json
pudl.egg-info/requires.txt
pudl.egg-info/top_level.txt
pudl/scripts/__init__.py
pudl/scripts/cli.py
pudl/test/__init__.py